{
  "id": 99006,
  "classname": "kasja_g2_bstonepath",
  "revision": 99006,
  "category": "other",
  "defaultdir": 0,
  "xdim": 1,
  "ydim": 1,
  "partcolors": {
    "color": []
  },
  "name": "Big Stone Path",
  "description": "",
  "adurl": "",
  "offerid": 99006,
  "buyout": true,
  "rentofferid": -1,
  "rentbuyout": false,
  "bc": false,
  "excludeddynamic": false,
  "customparams": "",
  "specialtype": 1,
  "canstandon": true,
  "cansiton": false,
  "canlayon": false,
  "furniline": "kasja_farm",
  "environment": "",
  "rare": false
}
